autonomous_claude/__init__.py
autonomous_claude/agent.py
autonomous_claude/cli.py
autonomous_claude/client.py
autonomous_claude/config.py
autonomous_claude/sandbox.py
autonomous_claude/ui.py
autonomous_claude/prompts/__init__.py
autonomous_claude/prompts/coding_prompt.md
autonomous_claude/prompts/setup_prompt.md
autonomous_claude-1.4.8.dist-info/METADATA
autonomous_claude-1.4.8.dist-info/WHEEL
autonomous_claude-1.4.8.dist-info/entry_points.txt
autonomous_claude-1.4.8.dist-info/licenses/LICENSE
autonomous_claude-1.4.8.dist-info/RECORD
