Metadata-Version: 2.4
Name: autonomous-claude
Version: 1.4.8
Summary: Build apps autonomously with Claude Code CLI
Project-URL: Homepage, https://github.com/ferdousbhai/autonomous-claude
Project-URL: Repository, https://github.com/ferdousbhai/autonomous-claude
Author: Ferdous Bhai
License-Expression: MIT
License-File: LICENSE
Keywords: ai,autonomous,claude,cli,coding
Classifier: Development Status :: 3 - Alpha
Classifier: Environment :: Console
Classifier: Intended Audience :: Developers
Classifier: License :: OSI Approved :: MIT License
Classifier: Programming Language :: Python :: 3
Classifier: Programming Language :: Python :: 3.10
Classifier: Programming Language :: Python :: 3.11
Classifier: Programming Language :: Python :: 3.12
Classifier: Topic :: Software Development
Requires-Python: >=3.10
Requires-Dist: rich>=13.0.0
Requires-Dist: tomli>=2.0.0; python_version < '3.11'
Requires-Dist: typer>=0.9.0
